SmartDocument/SmartDocument.py
SmartDocument/__init__.py
docassemble.integra-0.0.4.dist-info/LICENSE.txt
docassemble.integra-0.0.4.dist-info/METADATA
docassemble.integra-0.0.4.dist-info/WHEEL
docassemble.integra-0.0.4.dist-info/top_level.txt
docassemble.integra-0.0.4.dist-info/RECORD
