Metadata-Version: 2.1
Name: docassemble.integra
Version: 0.0.4
Summary: Generate a signed smart document
Home-page: https://github.com/alexeybreusov5/SmartDocument
Author: Alexey Breusov
Author-email: alexeybreusov5@gmail.com
License: UNKNOWN
Platform: UNKNOWN
Classifier: Programming Language :: Python :: 3
Classifier: License :: OSI Approved :: MIT License
Classifier: Operating System :: OS Independent
Requires-Python: >=3.6
